km2miles/__init__.py
km2miles/converter.py
km2miles-0.1.3.dist-info/METADATA
km2miles-0.1.3.dist-info/WHEEL
km2miles-0.1.3.dist-info/RECORD
