Metadata-Version: 2.3
Name: km2miles
Version: 0.1.3
Summary: A simple package to convert kilometers to miles.
License: MIT
Keywords: kilometers,miles,converter,distance,unit conversion
Author: Ali Beg
Author-email: mbeg937@gmail.com
Requires-Python: >=3.8,<4.0
Classifier: License :: OSI Approved :: MIT License
Classifier: Programming Language :: Python :: 3
Classifier: Programming Language :: Python :: 3.8
Classifier: Programming Language :: Python :: 3.9
Classifier: Programming Language :: Python :: 3.10
Classifier: Programming Language :: Python :: 3.11
Classifier: Programming Language :: Python :: 3.12
Classifier: Programming Language :: Python :: 3.13
Project-URL: Homepage, https://github.com/Ali-Beg/km2miles
Project-URL: Repository, https://github.com/Ali-Beg/km2miles
